pipomatic_hudge_po_data_pandas_ellipse.py
pipomatic_hudge_po_data_pandas_ellipse-1.0.dist-info/WHEEL
pipomatic_hudge_po_data_pandas_ellipse-1.0.dist-info/METADATA
pipomatic_hudge_po_data_pandas_ellipse-1.0.dist-info/RECORD
