Metadata-Version: 2.1
Name: pipomatic_hudge_po_data_pandas_ellipse
Version: 1.0
Summary: Helper functions for working with Ellipse PO reports
Home-page: http://www.mybusinessautomated.com
License: UNKNOWN
Author: Hudge
Author-email: doug@mybusinessautomated.com
Classifier: License :: OSI Approved :: MIT License
